bbq/__init__.py
bbq/bbq_code.py
bbq/polynomial.py
bbq/utils.py
bbq/examples/gross-code.ipynb
bbq/examples/other-codes.ipynb
bbq/examples/toric-code.ipynb
bbqudit-0.0.1.dist-info/METADATA
bbqudit-0.0.1.dist-info/WHEEL
bbqudit-0.0.1.dist-info/licenses/LICENSE
bbqudit-0.0.1.dist-info/RECORD
